<?xml version="1.0" encoding="UTF-8"?>
<Configuration>
    <WorldVsWorld>
        <!-- TODO include spawns, mercs, etc? -->

        <!-- Eternal Battlegrounds -->
        <Map height="1152" type="Center" width="1204" x="1448" y="1768">
            <!-- Top (red) -->
            <Objective code="Speldan" id="6" type="Camp" x="0" y="0" />
            <Objective code="Pangloss" id="5" type="Camp" x="0" y="0" />
            <Objective code="Mendon's" id="17" type="Tower" x="0" y="0" />
            <Objective code="Veloka" id="20" type="Tower" x="0" y="0" />
            <Objective code="Anzalias" id="18" type="Tower" x="0" y="0" />
            <Objective code="Ogrewatch" id="19" type="Tower" x="0" y="0" />
            <Objective code="Overlook" id="1" type="Keep" x="0" y="0" />

            <!-- Left (green) -->
            <Objective code="Rogue's" id="10" type="Camp" x="0" y="0" />
            <Objective code="Golanta" id="4" type="Camp" x="0" y="0" />
            <Objective code="Aldon's" id="11" type="Tower" x="0" y="0" />
            <Objective code="Wildcreek" id="12" type="Tower" x="0" y="0" />
            <Objective code="Jerrifer's" id="13" type="Tower" x="0" y="0" />
            <Objective code="Klovan" id="14" type="Tower" x="0" y="0" />
            <Objective code="Lowlands" id="3" type="Keep" x="0" y="0" />

            <!-- Right (blue) -->
            <Objective code="Danelon" id="7" type="Camp" x="0" y="0" />
            <Objective code="Umberglade" id="8" type="Camp" x="0" y="0" />
            <Objective code="Quentin" id="16" type="Tower" x="0" y="0" />
            <Objective code="Durios" id="21" type="Tower" x="0" y="0" />
            <Objective code="Langor" id="15" type="Tower" x="0" y="0" />
            <Objective code="Bravost" id="22" type="Tower" x="0" y="0" />
            <Objective code="Valley" id="2" type="Keep" x="0" y="0" />

            <!-- Neutral -->
            <Objective code="Stonemist" id="9" type="Castle" x="0" y="0" />
        </Map>

        <!-- Red Desert Borderlands -->
        <Map height="1185" type="RedHome" width="1196" x="1540" y="235">
            <Objective code="Northwest" id="115" type="Camp" x="0" y="0" />
            <Objective code="North" id="99" type="Camp" x="0" y="0" />
            <Objective code="Northeast" id="109" type="Camp" x="0" y="0" />
            <Objective code="Southwest" id="101" type="Camp" x="0" y="0" />
            <Objective code="South" id="116" type="Camp" x="0" y="0" />
            <Objective code="Southeast" id="100" type="Camp" x="0" y="0" />
            <Objective code="Northwest" id="102" type="Tower" x="0" y="0" />
            <Objective code="Northeast" id="104" type="Tower" x="0" y="0" />
            <Objective code="Southwest" id="110" type="Tower" x="0" y="0" />
            <Objective code="Southeast" id="105" type="Tower" x="0" y="0" />
            <Objective code="Fire" id="106" type="Keep" x="0" y="0" />
            <Objective code="Earth" id="113" type="Keep" x="0" y="0" />
            <Objective code="Air" id="114" type="Keep" x="0" y="0" />
        </Map>

        <!-- Blue Alpine Borderlands -->
        <Map height="1376" type="BlueHome" width="972" x="2952" y="1000">
            <Objective code="Northwest" id="52" type="Camp" x="0" y="0" />
            <Objective code="North" id="39" type="Camp" x="0" y="0" />
            <Objective code="Northeast" id="51" type="Camp" x="0" y="0" />
            <Objective code="Southwest" id="53" type="Camp" x="0" y="0" />
            <Objective code="South" id="34" type="Camp" x="0" y="0" />
            <Objective code="Southeast" id="50" type="Camp" x="0" y="0" />
            <Objective code="Northwest" id="38" type="Tower" x="0" y="0" />
            <Objective code="Northeast" id="40" type="Tower" x="0" y="0" />
            <Objective code="Southwest" id="35" type="Tower" x="0" y="0" />
            <Objective code="Southeast" id="36" type="Tower" x="0" y="0" />
            <Objective code="West" id="33" type="Keep" x="0" y="0" />
            <Objective code="North" id="37" type="Keep" x="0" y="0" />
            <Objective code="East" id="32" type="Keep" x="0" y="0" />
        </Map>

        <!-- Green Alpine Borderlands -->
        <Map height="1376" type="GreenHome" width="972" x="148" y="1244">
            <Objective code="Northwest" id="52" type="Camp" x="0" y="0" />
            <Objective code="North" id="39" type="Camp" x="0" y="0" />
            <Objective code="Northeast" id="51" type="Camp" x="0" y="0" />
            <Objective code="Southwest" id="53" type="Camp" x="0" y="0" />
            <Objective code="South" id="34" type="Camp" x="0" y="0" />
            <Objective code="Southeast" id="50" type="Camp" x="0" y="0" />
            <Objective code="Northwest" id="38" type="Tower" x="0" y="0" />
            <Objective code="Northeast" id="40" type="Tower" x="0" y="0" />
            <Objective code="Southwest" id="35" type="Tower" x="0" y="0" />
            <Objective code="Southeast" id="36" type="Tower" x="0" y="0" />
            <Objective code="West" id="33" type="Keep" x="0" y="0" />
            <Objective code="North" id="37" type="Keep" x="0" y="0" />
            <Objective code="East" id="32" type="Keep" x="0" y="0" />
        </Map>

        <!-- Edge of the Mists -->
        <Map height="1185" type="EdgeOfTheMists" width="1196" x="312" y="36" />
    </WorldVsWorld>
</Configuration>